LICENSE.txt
MANIFEST.in
README.rst
setup.py
docs/Makefile
docs/conf.py
docs/index.rst
tests/.coverage
tests/.coveragerc
tests/.gitignore
tests/10_test_model.py
tests/20_test_cli.py
tests/pytest.ini
tests/run_tests.py
tests/test_helpers.py
tests/two_cents.db
tests/htmlcov/_home_kale_hacking_hobbies_two_cents_two_cents___init__.html
tests/htmlcov/_home_kale_hacking_hobbies_two_cents_two_cents_banks.html
tests/htmlcov/_home_kale_hacking_hobbies_two_cents_two_cents_cli.html
tests/htmlcov/_home_kale_hacking_hobbies_two_cents_two_cents_model.html
tests/htmlcov/coverage_html.js
tests/htmlcov/index.html
tests/htmlcov/jquery.hotkeys.js
tests/htmlcov/jquery.isonscreen.js
tests/htmlcov/jquery.min.js
tests/htmlcov/jquery.tablesorter.min.js
tests/htmlcov/keybd_closed.png
tests/htmlcov/keybd_open.png
tests/htmlcov/status.dat
tests/htmlcov/style.css
two_cents/__init__.py
two_cents/banks.py
two_cents/cli.py
two_cents/model.py
two_cents.egg-info/PKG-INFO
two_cents.egg-info/SOURCES.txt
two_cents.egg-info/dependency_links.txt
two_cents.egg-info/entry_points.txt
two_cents.egg-info/not-zip-safe
two_cents.egg-info/requires.txt
two_cents.egg-info/top_level.txt