Metadata-Version: 1.1
Name: two-cents
Version: 1.0.1
Summary: UNKNOWN
Home-page: https://github.com/kalekundert/two_cents
Author: Kale Kundert
Author-email: kale@thekunderts.net
License: UNKNOWN
Keywords: two_cents
Platform: UNKNOWN
Classifier: Development Status :: 2 - Pre-Alpha
Classifier: Natural Language :: English
Classifier: Programming Language :: Python :: 3
Classifier: Programming Language :: Python :: 3.3
Classifier: Programming Language :: Python :: 3.4
Classifier: Programming Language :: Python :: 3.5
